README.md
setup.py
rainbowmindmachine/PhotoADaySheep.py
rainbowmindmachine/PoemSheep.py
rainbowmindmachine/QueneauSheep.py
rainbowmindmachine/SocialSheep.py
rainbowmindmachine/TwitterKeymaker.py
rainbowmindmachine/TwitterSheep.py
rainbowmindmachine/TwitterShepherd.py
rainbowmindmachine/__init__.py
rainbowmindmachine/apikeys.example.py
rainbowmindmachine/queneau.py
rainbowmindmachine.egg-info/PKG-INFO
rainbowmindmachine.egg-info/SOURCES.txt
rainbowmindmachine.egg-info/dependency_links.txt
rainbowmindmachine.egg-info/not-zip-safe
rainbowmindmachine.egg-info/requires.txt
rainbowmindmachine.egg-info/top_level.txt