Metadata-Version: 1.0
Name: rainbowmindmachine
Version: 23.1
Summary: The extensible framework for running Twitter bot flocks.
Home-page: https://pages.charlesreid1.com/rainbow-mind-machine
Author: charlesreid1
Author-email: rainbowmindmachine@charlesreid1.com
License: MIT
Platform: UNKNOWN
